HW2/adder.v
// Adder circuit

module behavioralFullAdder
(
    output sum, 
    output carryout,
    input a, 
    input b, 
    input carryin
);
    // Uses concatenation operator and built-in '+'
    assign {carryout, sum}=a+b+carryin;
endmodule

module structuralFullAdder
(
    output sum, 
    output carryout,
    input a, 
    input b, 
    input c
);

	wire axb, axbxc, ab, bc, ac, abc, abubc; 

	xor axb_(axb, a, b);
	xor axbxc_(axbxc, axb, c);

	and ab_(ab, a, b);
	and ac_(ac, a, c);
	and bc_(bc, b, c);
	and abc_(abc, ab, c);

	or sum_(sum, axbxc, abc);

	or abubc_(abubc, ab, bc);
	or carryout_(carryout, abubc, ac);
endmodule

HW2/adder.t.v
// Adder testbench
`timescale 1 ns / 1 ps
`include "adder.v"

module testFullAdder();
    reg a, b, cIn;
    wire sum, cOut;

    //behavioralFullAdder adder (sum, cOut, a, b, cIn);
		structuralFullAdder adder(sum, cOut, a, b, cIn);

    initial begin
			$display("a b cIn | sum cOut | expected sum cOut");
			a = 0; b = 0; cIn = 0; #1000
			$display("%b %b  %b  |  %b   %b   |           0   0", a, b, cIn, sum, cOut);
			a = 0; b = 0; cIn = 1; #1000
			$display("%b %b  %b  |  %b   %b   |           1   0", a, b, cIn, sum, cOut);
			a = 0; b = 1; cIn = 0; #1000
			$display("%b %b  %b  |  %b   %b   |           1   0", a, b, cIn, sum, cOut);
			a = 0; b = 1; cIn = 1; #1000
			$display("%b %b  %b  |  %b   %b   |           0   1", a, b, cIn, sum, cOut);
			a = 1; b = 0; cIn = 0; #1000
			$display("%b %b  %b  |  %b   %b   |           1   0", a, b, cIn, sum, cOut);
			a = 1; b = 0; cIn = 1; #1000
			$display("%b %b  %b  |  %b   %b   |           0   1", a, b, cIn, sum, cOut);
			a = 1; b = 1; cIn = 0; #1000
			$display("%b %b  %b  |  %b   %b   |           0   1", a, b, cIn, sum, cOut);
			a = 1; b = 1; cIn = 1; #1000
			$display("%b %b  %b  |  %b   %b   |           1   1", a, b, cIn, sum, cOut);
    end

		initial begin
			$dumpfile("adder.vcd");
			$dumpvars(0, testFullAdder);
		end

endmodule

HW2/Results/adder.vcd
$date
	Sun Sep 16 21:31:23 2018
$end
$version
	Icarus Verilog
$end
$timescale
	1ps
$end
$scope module testFullAdder $end
$var wire 1 ! sum $end
$var wire 1 " cOut $end
$var reg 1 # a $end
$var reg 1 $ b $end
$var reg 1 % cIn $end
$scope module adder $end
$var wire 1 # a $end
$var wire 1 & ab $end
$var wire 1 ' abc $end
$var wire 1 ( abubc $end
$var wire 1 ) ac $end
$var wire 1 * axb $end
$var wire 1 + axbxc $end
$var wire 1 $ b $end
$var wire 1 , bc $end
$var wire 1 % c $end
$var wire 1 " carryout $end
$var wire 1 ! sum $end
$upscope $end
$upscope $end
$enddefinitions $end
#0
$dumpvars
x,
x+
x*
x)
x(
x'
x&
0%
0$
0#
x"
x!
$end
#50000
0'
0,
0)
0&
0*
#100000
0(
0+
#150000
0"
0!
#1000000
1%
#1050000
1+
#1100000
1!
#2000000
0%
1$
#2050000
0+
1*
#2100000
0!
1+
#2150000
1!
#3000000
1%
#3050000
0+
1,
#3100000
0!
1(
#3150000
1"
#4000000
0%
0$
1#
#4050000
1+
0,
#4100000
1!
0(
#4150000
0"
#5000000
1%
#5050000
0+
1)
#5100000
0!
1"
#6000000
0%
1$
#6050000
1+
0)
0*
1&
#6100000
1!
0"
0+
1(
#6150000
0!
1"
#7000000
1%
#7050000
1+
1)
1,
1'
#7100000
1!
