HW2/decoder.v
// Decoder circuit
`define NOT not #50
`define AND and #50

module behavioralDecoder
(
    output out0, out1, out2, out3,
    input address0, address1,
    input enable
);
    // Uses concatenation and shift operators
    assign {out3,out2,out1,out0}=enable<<{address1,address0};
endmodule

module structuralDecoder
(
    output o0, o1, o2, o3,
    input a0, a1,
    input e
);

	wire na0, na1;
	wire a0int, a1int, a2int, a3int;

	`NOT n_a0(na0, a0);
	`NOT n_a1(na1, a1);
	
	`AND o0_and(o0int, na0, na1);
	`AND o1_and(o1int, a0, na1);
	`AND o2_and(o2int, na0, a1);
	`AND o3_and(o3int, a0, a1);

	`AND o0_and2(o0, o0int, e);
	`AND o1_and2(o1, o1int, e);
	`AND o2_and2(o2, o2int, e);
	`AND o3_and2(o3, o3int, e);

endmodule

HW2/decoder.t.v
// Decoder testbench
`timescale 1 ns / 1 ps
`include "decoder.v"

module testDecoder (); 
    reg addr0, addr1;
    reg enable;
    wire out0,out1,out2,out3;

    //behavioralDecoder decoder (out0,out1,out2,out3,addr0,addr1,enable);
    structuralDecoder decoder (out0,out1,out2,out3,addr0,addr1,enable); 

    initial begin
    $display("En A0 A1| O0 O1 O2 O3 | Expected Output");
    enable=0;addr0=0;addr1=0; #1000 
    $display("%b  %b  %b |  %b  %b  %b  %b | All false", enable, addr0, addr1, out0, out1, out2, out3);
    enable=0;addr0=1;addr1=0; #1000
    $display("%b  %b  %b |  %b  %b  %b  %b | All false", enable, addr0, addr1, out0, out1, out2, out3);
    enable=0;addr0=0;addr1=1; #1000 
    $display("%b  %b  %b |  %b  %b  %b  %b | All false", enable, addr0, addr1, out0, out1, out2, out3);
    enable=0;addr0=1;addr1=1; #1000 
    $display("%b  %b  %b |  %b  %b  %b  %b | All false", enable, addr0, addr1, out0, out1, out2, out3);
    enable=1;addr0=0;addr1=0; #1000 
    $display("%b  %b  %b |  %b  %b  %b  %b | O0 Only", enable, addr0, addr1, out0, out1, out2, out3);
    enable=1;addr0=1;addr1=0; #1000 
    $display("%b  %b  %b |  %b  %b  %b  %b | O1 Only", enable, addr0, addr1, out0, out1, out2, out3);
    enable=1;addr0=0;addr1=1; #1000 
    $display("%b  %b  %b |  %b  %b  %b  %b | O2 Only", enable, addr0, addr1, out0, out1, out2, out3);
    enable=1;addr0=1;addr1=1; #1000 
    $display("%b  %b  %b |  %b  %b  %b  %b | O3 Only", enable, addr0, addr1, out0, out1, out2, out3);
    end

		initial begin
			$dumpfile("decoder.vcd");
			$dumpvars(0, testDecoder);
		end

endmodule

HW2/Results/decoder.vcd
$date
	Sun Sep 16 21:42:43 2018
$end
$version
	Icarus Verilog
$end
$timescale
	1ps
$end
$scope module testDecoder $end
$var wire 1 ! out3 $end
$var wire 1 " out2 $end
$var wire 1 # out1 $end
$var wire 1 $ out0 $end
$var reg 1 % addr0 $end
$var reg 1 & addr1 $end
$var reg 1 ' enable $end
$scope module decoder $end
$var wire 1 % a0 $end
$var wire 1 & a1 $end
$var wire 1 ' e $end
$var wire 1 ( na0 $end
$var wire 1 ) na1 $end
$var wire 1 $ o0 $end
$var wire 1 * o0int $end
$var wire 1 # o1 $end
$var wire 1 + o1int $end
$var wire 1 " o2 $end
$var wire 1 , o2int $end
$var wire 1 ! o3 $end
$var wire 1 - o3int $end
$upscope $end
$upscope $end
$enddefinitions $end
#0
$dumpvars
x-
x,
x+
x*
x)
x(
0'
0&
0%
x$
x#
x"
x!
$end
#50000
1)
1(
0!
0"
0#
0$
0-
0,
0+
#100000
1*
#1000000
1%
#1050000
0(
1+
#1100000
0*
#2000000
1&
0%
#2050000
0)
1(
0+
#2100000
1,
#3000000
1%
#3050000
0(
1-
#3100000
0,
#4000000
0&
0%
1'
#4050000
1)
1(
0-
1!
#4100000
1*
0!
#4150000
1$
#5000000
1%
#5050000
0(
1+
#5100000
0*
1#
#5150000
0$
#6000000
1&
0%
#6050000
0)
1(
0+
#6100000
1,
0#
#6150000
1"
#7000000
1%
#7050000
0(
1-
#7100000
0,
1!
#7150000
0"
