HW2/multiplexer.v
// Multiplexer circuit
`define NOT not #50
`define AND and #50
`define OR or #50

module behavioralMultiplexer
(
    output out,
    input address0, address1,
    input in0, in1, in2, in3
);
    // Join single-bit inputs into a bus, use address as index
    wire[3:0] inputs = {in3, in2, in1, in0};
    wire[1:0] address = {address1, address0};
    assign out = inputs[address];
endmodule


module structuralMultiplexer
(
    output out,
    input a0, a1,
    input in0, in1, in2, in3
);

	wire na0, na1, if0 /*"input filtered"*/, if1, if2, if3, if01, if23;

	`NOT na0_(na0, a0);
	`NOT na1_(na1, a1);

	wire ii0;
	`AND ii0_(ii0, in0, na0);
	`AND if0_(if0, ii0, na1);

	wire ii1;
	`AND ii1_(ii1, in1, a0);
	`AND if1_(if1, ii1, na1);

	wire ii2;
	`AND ii2_(ii2, in2, na0);
	`AND if2_(if2, ii2, a1);

	wire ii3;
	`AND ii3_(ii3, in3, a0);
	`AND if3_(if3, ii3, a1);

	`OR if01_(if01, if0, if1);
	`OR if23_(if23, if2, if3);
	`OR out_(out, if01, if23);

endmodule

HW2/multiplexer.t.v
// Multiplexer testbench
`timescale 1 ns / 1 ps
`include "multiplexer.v"

module testMultiplexer ();
	reg i1, i2, i3, i4, a1, a2; // indexed from 1.  fight me
	wire out;

	//behavioralMultiplexer mux(out, a1, a2, i1, i2, i3, i4);
	structuralMultiplexer mux(out, a1, a2, i1, i2, i3, i4);

	initial begin
		$display("i1 i2 i3 i4 | a1 a2 | out | expected out");
		i1 = 0; i2 = 0; i3 = 0; i4 = 0; a1 = 0; a2 = 0; #1000
		$display("%b  %b  %b  %b  | %b  %b  |  %b  |           0", i1, i2, i3, i4, a1, a2, out);
		i1 = 1; i2 = 0; i3 = 0; i4 = 0; a1 = 0; a2 = 0; #1000
		$display("%b  %b  %b  %b  | %b  %b  |  %b  |           1", i1, i2, i3, i4, a1, a2, out);
		i1 = 0; i2 = 1; i3 = 0; i4 = 0; a1 = 1; a2 = 0; #1000
		$display("%b  %b  %b  %b  | %b  %b  |  %b  |           1", i1, i2, i3, i4, a1, a2, out);
		i1 = 0; i2 = 0; i3 = 1; i4 = 0; a1 = 0; a2 = 1; #1000
		$display("%b  %b  %b  %b  | %b  %b  |  %b  |           1", i1, i2, i3, i4, a1, a2, out);
		i1 = 0; i2 = 0; i3 = 0; i4 = 1; a1 = 1; a2 = 1; #1000
		$display("%b  %b  %b  %b  | %b  %b  |  %b  |           1", i1, i2, i3, i4, a1, a2, out);
	end

		initial begin
			$dumpfile("mux.vcd");
			$dumpvars(0, testMultiplexer);
		end

endmodule

HW2/Results/mux.vcd
$date
	Sun Sep 16 21:31:16 2018
$end
$version
	Icarus Verilog
$end
$timescale
	1ps
$end
$scope module testMultiplexer $end
$var wire 1 ! out $end
$var reg 1 " a1 $end
$var reg 1 # a2 $end
$var reg 1 $ i1 $end
$var reg 1 % i2 $end
$var reg 1 & i3 $end
$var reg 1 ' i4 $end
$scope module mux $end
$var wire 1 " a0 $end
$var wire 1 # a1 $end
$var wire 1 ( if0 $end
$var wire 1 ) if01 $end
$var wire 1 * if1 $end
$var wire 1 + if2 $end
$var wire 1 , if23 $end
$var wire 1 - if3 $end
$var wire 1 . ii0 $end
$var wire 1 / ii1 $end
$var wire 1 0 ii2 $end
$var wire 1 1 ii3 $end
$var wire 1 $ in0 $end
$var wire 1 % in1 $end
$var wire 1 & in2 $end
$var wire 1 ' in3 $end
$var wire 1 2 na0 $end
$var wire 1 3 na1 $end
$var wire 1 ! out $end
$upscope $end
$upscope $end
$enddefinitions $end
#0
$dumpvars
x3
x2
x1
x0
x/
x.
x-
x,
x+
x*
x)
x(
0'
0&
0%
0$
0#
0"
x!
$end
#50000
13
12
0-
01
0+
00
0/
0.
#100000
0,
0*
0(
#150000
0)
#200000
0!
#1000000
1$
#1050000
1.
#1100000
1(
#1150000
1)
#1200000
1!
#2000000
1"
1%
0$
#2050000
02
1/
0.
#2100000
1*
0(
#3000000
1#
0"
1&
0%
#3050000
03
12
0/
#3100000
10
0*
#3150000
1+
0)
#3200000
1,
0!
#3250000
1!
#4000000
1"
1'
0&
#4050000
02
11
00
#4100000
1-
0+
